{
  "resourceType": "Bundle",
  "id": "86e31dbc-a80f-bf67-9244-fa5880a44236",
  "type": "transaction",
  "entry": [ {
    "fullUrl": "urn:uuid:5538f551-1633-35ca-a72a-a314c91a87ab",
    "resource": {
      "resourceType": "Practitioner",
      "id": "5538f551-1633-35ca-a72a-a314c91a87ab",
      "meta": {
        "profile": [ "http://hl7.org/fhir/us/core/StructureDefinition/us-core-practitioner" ]
      },
      "identifier": [ {
        "system": "http://hl7.org/fhir/sid/us-npi",
        "value": "9999999995"
      } ],
      "active": true,
      "name": [ {
        "family": "Hinojosa",
        "given": [ "Daniela" ],
        "prefix": [ "Dr." ]
      } ],
      "telecom": [ {
        "extension": [ {
          "url": "http://hl7.org/fhir/us/core/StructureDefinition/us-core-direct",
          "valueBoolean": true
        } ],
        "system": "email",
        "value": "Daniela.Hinojosa@example.com",
        "use": "work"
      } ],
      "address": [ {
        "line": [ "60 HOSPITAL ROAD" ],
        "city": "LEOMINSTER",
        "state": "MA",
        "postalCode": "01453",
        "country": "US"
      } ],
      "gender": "female"
    },
    "request": {
      "method": "POST",
      "url": "Practitioner",
      "ifNoneExist": "identifier=http://hl7.org/fhir/sid/us-npi|9999999995"
    }
  }, {
    "fullUrl": "urn:uuid:7f4529e5-dace-e517-7d98-177b47da8c68",
    "resource": {
      "resourceType": "PractitionerRole",
      "id": "7f4529e5-dace-e517-7d98-177b47da8c68",
      "meta": {
        "profile": [ "http://hl7.org/fhir/us/core/StructureDefinition/us-core-practitionerrole" ]
      },
      "practitioner": {
        "identifier": {
          "system": "http://hl7.org/fhir/sid/us-npi",
          "value": "9999999995"
        },
        "display": "Dr. Daniela Hinojosa"
      },
      "organization": {
        "identifier": {
          "system": "https://github.com/synthetichealth/synthea",
          "value": "363d3504-18f8-37de-8fbb-f52a59fd61b1"
        },
        "display": "\"HEALTHALLIANCE HOSPITALS, INC\""
      },
      "code": [ {
        "coding": [ {
          "system": "http://nucc.org/provider-taxonomy",
          "code": "208D00000X",
          "display": "General Practice"
        } ],
        "text": "General Practice"
      } ],
      "specialty": [ {
        "coding": [ {
          "system": "http://nucc.org/provider-taxonomy",
          "code": "208D00000X",
          "display": "General Practice"
        } ],
        "text": "General Practice"
      } ],
      "location": [ {
        "identifier": {
          "system": "https://github.com/synthetichealth/synthea",
          "value": "d0e312f3-0a19-3089-af0e-db79b3aee7ab"
        },
        "display": "\"HEALTHALLIANCE HOSPITALS, INC\""
      } ],
      "telecom": [ {
        "system": "phone",
        "value": "9784662000"
      }, {
        "extension": [ {
          "url": "http://hl7.org/fhir/us/core/StructureDefinition/us-core-direct",
          "valueBoolean": true
        } ],
        "system": "email",
        "value": "Daniela.Hinojosa@example.com",
        "use": "work"
      } ]
    },
    "request": {
      "method": "POST",
      "url": "PractitionerRole"
    }
  }, {
    "fullUrl": "urn:uuid:5538f551-1633-35ca-a72a-a314c91a87ab",
    "resource": {
      "resourceType": "Practitioner",
      "id": "5538f551-1633-35ca-a72a-a314c91a87ab",
      "meta": {
        "profile": [ "http://hl7.org/fhir/us/core/StructureDefinition/us-core-practitioner" ]
      },
      "identifier": [ {
        "system": "http://hl7.org/fhir/sid/us-npi",
        "value": "9999999995"
      } ],
      "active": true,
      "name": [ {
        "family": "Hinojosa",
        "given": [ "Daniela" ],
        "prefix": [ "Dr." ]
      } ],
      "telecom": [ {
        "extension": [ {
          "url": "http://hl7.org/fhir/us/core/StructureDefinition/us-core-direct",
          "valueBoolean": true
        } ],
        "system": "email",
        "value": "Daniela.Hinojosa@example.com",
        "use": "work"
      } ],
      "address": [ {
        "line": [ "60 HOSPITAL ROAD" ],
        "city": "LEOMINSTER",
        "state": "MA",
        "postalCode": "01453",
        "country": "US"
      } ],
      "gender": "female"
    },
    "request": {
      "method": "POST",
      "url": "Practitioner",
      "ifNoneExist": "identifier=http://hl7.org/fhir/sid/us-npi|9999999995"
    }
  }, {
    "fullUrl": "urn:uuid:db0f58d9-cd14-fe1c-5268-8d6d06af3659",
    "resource": {
      "resourceType": "PractitionerRole",
      "id": "db0f58d9-cd14-fe1c-5268-8d6d06af3659",
      "meta": {
        "profile": [ "http://hl7.org/fhir/us/core/StructureDefinition/us-core-practitionerrole" ]
      },
      "practitioner": {
        "identifier": {
          "system": "http://hl7.org/fhir/sid/us-npi",
          "value": "9999999995"
        },
        "display": "Dr. Daniela Hinojosa"
      },
      "organization": {
        "identifier": {
          "system": "https://github.com/synthetichealth/synthea",
          "value": "363d3504-18f8-37de-8fbb-f52a59fd61b1"
        },
        "display": "\"HEALTHALLIANCE HOSPITALS, INC\""
      },
      "code": [ {
        "coding": [ {
          "system": "http://nucc.org/provider-taxonomy",
          "code": "208D00000X",
          "display": "General Practice"
        } ],
        "text": "General Practice"
      } ],
      "specialty": [ {
        "coding": [ {
          "system": "http://nucc.org/provider-taxonomy",
          "code": "208D00000X",
          "display": "General Practice"
        } ],
        "text": "General Practice"
      } ],
      "location": [ {
        "identifier": {
          "system": "https://github.com/synthetichealth/synthea",
          "value": "d0e312f3-0a19-3089-af0e-db79b3aee7ab"
        },
        "display": "\"HEALTHALLIANCE HOSPITALS, INC\""
      } ],
      "telecom": [ {
        "system": "phone",
        "value": "9784662000"
      }, {
        "extension": [ {
          "url": "http://hl7.org/fhir/us/core/StructureDefinition/us-core-direct",
          "valueBoolean": true
        } ],
        "system": "email",
        "value": "Daniela.Hinojosa@example.com",
        "use": "work"
      } ]
    },
    "request": {
      "method": "POST",
      "url": "PractitionerRole"
    }
  }, {
    "resource": {
      "resourceType": "Parameters",
      "id": "86e31dbc-a80f-bf67-9244-fa5880a44236.scorekey",
      "parameter": [ {
        "name": "InitialPopulation",
        "valueBoolean": false
      }, {
        "name": "ContinuousEnrollment",
        "valueBoolean": true
      }, {
        "name": "InitialPopulation",
        "valueBoolean": false
      }, {
        "name": "Denominator",
        "valueBoolean": false
      }, {
        "name": "RequiredExclusion",
        "valueBoolean": true
      }, {
        "name": "RequiredExclusion",
        "valueBoolean": true
      }, {
        "name": "Numerator_2",
        "valueBoolean": true
      }, {
        "name": "ContinuousEnrollment",
        "valueBoolean": true
      }, {
        "name": "Numerator_1",
        "valueBoolean": false
      }, {
        "name": "Numerator_4",
        "valueBoolean": true
      }, {
        "name": "Numerator_3",
        "valueBoolean": false
      }, {
        "name": "Denominator",
        "valueBoolean": false
      }, {
        "name": "RequiredExclusion",
        "valueBoolean": true
      }, {
        "name": "Numerator_1",
        "valueBoolean": false
      }, {
        "name": "ContinuousEnrollment",
        "valueBoolean": true
      }, {
        "name": "Numerator_3",
        "valueBoolean": false
      }, {
        "name": "Numerator_2",
        "valueBoolean": true
      }, {
        "name": "Numerator_4",
        "valueBoolean": true
      }, {
        "name": "RequiredExclusion",
        "valueBoolean": true
      }, {
        "name": "Numerator_4",
        "valueBoolean": true
      }, {
        "name": "Numerator_3",
        "valueBoolean": false
      }, {
        "name": "Numerator_2",
        "valueBoolean": true
      }, {
        "name": "Numerator_2",
        "valueBoolean": true
      }, {
        "name": "InitialPopulation",
        "valueBoolean": false
      }, {
        "name": "Numerator_1",
        "valueBoolean": false
      }, {
        "name": "RequiredExclusion",
        "valueBoolean": true
      } ]
    }
  }, {
    "resource": {
      "resourceType": "Parameters",
      "id": "86e31dbc-a80f-bf67-9244-fa5880a44236.all-params",
      "parameter": [ {
        "name": "dsu_continuous_enrollment.json Module.Start Date",
        "valueString": "01/01/2024"
      }, {
        "name": "dsu.json Module.Measurement_Period_End",
        "valueString": "12/31/2024"
      }, {
        "name": "dsu.json Module.Prior_Year_Start",
        "valueString": "01/01/2022"
      }, {
        "name": "dsu.json Module.Prior_Year_End",
        "valueString": "12/31/2023"
      }, {
        "name": "dsu_denominator.json Module.InitialPopulation",
        "valueBoolean": false
      }, {
        "name": "dsu_continuous_enrollment.json Module.ContinuousEnrollment",
        "valueBoolean": true
      }, {
        "name": "dsu.json Module.InitialPopulation",
        "valueBoolean": false
      }, {
        "name": "dsu_denominator.json Module.Denominator",
        "valueBoolean": false
      }, {
        "name": "dsu_denominator.json Module.RequiredExclusion",
        "valueBoolean": true
      }, {
        "name": "dsu.json Module.RequiredExclusion",
        "valueBoolean": true
      }, {
        "name": "dsu_numerator.json Module.Numerator_2",
        "valueBoolean": true
      }, {
        "name": "dsu.json Module.ContinuousEnrollment",
        "valueBoolean": true
      }, {
        "name": "dsu_numerator.json Module.Numerator_1",
        "valueBoolean": false
      }, {
        "name": "dsu_numerator.json Module.Numerator_4",
        "valueBoolean": true
      }, {
        "name": "dsu_numerator.json Module.Numerator_3",
        "valueBoolean": false
      }, {
        "name": "dsu.json Module.Denominator",
        "valueBoolean": false
      }, {
        "name": "hospice_check.json Module.RequiredExclusion",
        "valueBoolean": true
      }, {
        "name": "dsu_numerator_check.json Module.Numerator_1",
        "valueBoolean": false
      }, {
        "name": "dsu_initial_population.json Module.ContinuousEnrollment",
        "valueBoolean": true
      }, {
        "name": "dsu_numerator_check.json Module.Numerator_3",
        "valueBoolean": false
      }, {
        "name": "dsu_numerator_check.json Module.Numerator_2",
        "valueBoolean": true
      }, {
        "name": "dsu_numerator_check.json Module.Numerator_4",
        "valueBoolean": true
      }, {
        "name": "dsu_initial_population.json Module.RequiredExclusion",
        "valueBoolean": true
      }, {
        "name": "dsu.json Module.Numerator_4",
        "valueBoolean": true
      }, {
        "name": "dsu.json Module.Numerator_3",
        "valueBoolean": false
      }, {
        "name": "dsu_numerator_2.json Module.Numerator_2",
        "valueBoolean": true
      }, {
        "name": "dsu.json Module.Numerator_2",
        "valueBoolean": true
      }, {
        "name": "dsu_initial_population.json Module.InitialPopulation",
        "valueBoolean": false
      }, {
        "name": "dsu.json Module.Numerator_1",
        "valueBoolean": false
      }, {
        "name": "hospice_required_exclusion.json Module.RequiredExclusion",
        "valueBoolean": true
      } ]
    }
  }, {
    "fullUrl": "urn:uuid:86e31dbc-a80f-bf67-9244-fa5880a44236",
    "resource": {
      "resourceType": "Patient",
      "id": "86e31dbc-a80f-bf67-9244-fa5880a44236",
      "meta": {
        "profile": [ "http://hl7.org/fhir/us/core/StructureDefinition/us-core-patient" ]
      },
      "text": {
        "status": "generated",
        "div": "<div xmlns=\"http://www.w3.org/1999/xhtml\">Generated by <a href=\"https://github.com/synthetichealth/synthea\">Synthea</a>.Version identifier: 79d417f\n .   Person seed: 6907249309107868067  Population seed: 1703176669956</div>"
      },
      "extension": [ {
        "url": "http://hl7.org/fhir/us/core/StructureDefinition/us-core-race",
        "extension": [ {
          "url": "ombCategory",
          "valueCoding": {
            "system": "urn:oid:2.16.840.1.113883.6.238",
            "code": "2028-9",
            "display": "Asian"
          }
        }, {
          "url": "text",
          "valueString": "Asian"
        } ]
      }, {
        "url": "http://hl7.org/fhir/us/core/StructureDefinition/us-core-ethnicity",
        "extension": [ {
          "url": "ombCategory",
          "valueCoding": {
            "system": "urn:oid:2.16.840.1.113883.6.238",
            "code": "2186-5",
            "display": "Not Hispanic or Latino"
          }
        }, {
          "url": "text",
          "valueString": "Not Hispanic or Latino"
        } ]
      }, {
        "url": "http://hl7.org/fhir/StructureDefinition/patient-mothersMaidenName",
        "valueString": "Latarsha Koss"
      }, {
        "url": "http://hl7.org/fhir/us/core/StructureDefinition/us-core-birthsex",
        "valueCode": "F"
      }, {
        "url": "http://hl7.org/fhir/StructureDefinition/patient-birthPlace",
        "valueAddress": {
          "city": "Busan",
          "state": "Busan",
          "country": "KR"
        }
      } ],
      "identifier": [ {
        "system": "https://github.com/synthetichealth/synthea",
        "value": "86e31dbc-a80f-bf67-9244-fa5880a44236"
      }, {
        "type": {
          "coding": [ {
            "system": "http://terminology.hl7.org/CodeSystem/v2-0203",
            "code": "MR",
            "display": "Medical Record Number"
          } ],
          "text": "Medical Record Number"
        },
        "system": "http://hospital.smarthealthit.org",
        "value": "86e31dbc-a80f-bf67-9244-fa5880a44236"
      }, {
        "type": {
          "coding": [ {
            "system": "http://terminology.hl7.org/CodeSystem/v2-0203",
            "code": "SS",
            "display": "Social Security Number"
          } ],
          "text": "Social Security Number"
        },
        "system": "http://hl7.org/fhir/sid/us-ssn",
        "value": "999-87-8117"
      } ],
      "name": [ {
        "use": "official",
        "family": "Nolan",
        "given": [ "Charmaine", "Jame" ]
      } ],
      "telecom": [ {
        "system": "phone",
        "value": "555-375-8460",
        "use": "home"
      } ],
      "gender": "female",
      "birthDate": "2009-05-07",
      "address": [ {
        "extension": [ {
          "url": "http://hl7.org/fhir/StructureDefinition/geolocation",
          "extension": [ {
            "url": "latitude",
            "valueDecimal": 42.30348299934432
          }, {
            "url": "longitude",
            "valueDecimal": -71.65300523415597
          } ]
        } ],
        "line": [ "549 Schaden Glen Unit 87" ],
        "city": "Westborough",
        "state": "MA",
        "postalCode": "01581",
        "country": "US"
      } ],
      "maritalStatus": {
        "coding": [ {
          "system": "http://terminology.hl7.org/CodeSystem/v3-MaritalStatus",
          "code": "S",
          "display": "Never Married"
        } ],
        "text": "Never Married"
      },
      "multipleBirthBoolean": false,
      "communication": [ {
        "language": {
          "coding": [ {
            "system": "urn:ietf:bcp:47",
            "code": "ko",
            "display": "Korean"
          } ],
          "text": "Korean"
        }
      } ]
    }
  }, {
    "fullUrl": "urn:uuid:198bcfce-31c4-6d23-7eb5-a2fe40f778e9",
    "resource": {
      "resourceType": "Claim",
      "id": "198bcfce-31c4-6d23-7eb5-a2fe40f778e9",
      "meta": {
        "tag": [ {
          "system": "https://ncqa.org/fhir/CodeSystem/synthea-state-id",
          "code": "3676e0c0-e9c9-46f9-b422-db2b5a8d9425",
          "display": "Synthea State Id that generated the resource"
        }, {
          "system": "https://ncqa.org/fhir/CodeSystem/hedis-data-source",
          "code": "administrative"
        } ]
      },
      "status": "active",
      "type": {
        "coding": [ {
          "system": "http://terminology.hl7.org/CodeSystem/claim-type",
          "code": "institutional"
        } ]
      },
      "use": "claim",
      "patient": {
        "reference": "urn:uuid:86e31dbc-a80f-bf67-9244-fa5880a44236",
        "display": "Charmaine Nolan"
      },
      "billablePeriod": {
        "start": "2024-01-31T00:00:00+00:00",
        "end": "2024-01-31T00:15:00+00:00"
      },
      "created": "2024-01-31T00:15:00+00:00",
      "provider": {
        "reference": "Organization?identifier=https://github.com/synthetichealth/synthea|363d3504-18f8-37de-8fbb-f52a59fd61b1",
        "display": "\"HEALTHALLIANCE HOSPITALS, INC\""
      },
      "priority": {
        "coding": [ {
          "system": "http://terminology.hl7.org/CodeSystem/processpriority",
          "code": "normal"
        } ]
      },
      "diagnosis": [ {
        "sequence": 1,
        "diagnosisReference": {
          "reference": "urn:uuid:bad8210d-5775-b57c-73ba-0ffd246e38f0",
          "display": "Opioid Abuse & Dep ICD 10 Dx Only"
        }
      } ],
      "item": [ {
        "sequence": 1,
        "diagnosisSequence": [ 1 ],
        "productOrService": {
          "coding": [ {
            "system": "http://www.ama-assn.org/go/cpt",
            "code": "99348"
          } ]
        },
        "servicedPeriod": {
          "start": "2024-01-31T00:00:00+00:00",
          "end": "2024-01-31T00:15:00+00:00"
        }
      } ]
    }
  }, {
    "fullUrl": "urn:uuid:bad8210d-5775-b57c-73ba-0ffd246e38f0",
    "resource": {
      "resourceType": "Condition",
      "id": "bad8210d-5775-b57c-73ba-0ffd246e38f0",
      "meta": {
        "profile": [ "http://hl7.org/fhir/us/core/StructureDefinition/us-core-condition" ],
        "tag": [ {
          "system": "https://ncqa.org/fhir/CodeSystem/synthea-state-id",
          "code": "6feebda2-5941-446c-a6ef-b6786b3f1544",
          "display": "Synthea State Id that generated the resource"
        } ]
      },
      "clinicalStatus": {
        "coding": [ {
          "system": "http://terminology.hl7.org/CodeSystem/condition-clinical",
          "code": "active"
        } ]
      },
      "verificationStatus": {
        "coding": [ {
          "system": "http://terminology.hl7.org/CodeSystem/condition-ver-status",
          "code": "confirmed"
        } ]
      },
      "category": [ {
        "coding": [ {
          "system": "http://terminology.hl7.org/CodeSystem/condition-category",
          "code": "encounter-diagnosis",
          "display": "Encounter Diagnosis"
        } ]
      } ],
      "code": {
        "coding": [ {
          "system": "http://hl7.org/fhir/sid/icd-10-cm",
          "code": "F11.221",
          "display": "[F11.221] Opioid dependence with intoxication delirium"
        } ],
        "text": "[F11.221] Opioid dependence with intoxication delirium"
      },
      "subject": {
        "reference": "urn:uuid:86e31dbc-a80f-bf67-9244-fa5880a44236"
      },
      "onsetDateTime": "2024-01-31T00:00:00+00:00",
      "recordedDate": "2024-01-31T00:00:00+00:00"
    }
  }, {
    "fullUrl": "urn:uuid:122ae231-75de-503e-7718-04b9a38a3a8f",
    "resource": {
      "resourceType": "Encounter",
      "id": "122ae231-75de-503e-7718-04b9a38a3a8f",
      "meta": {
        "profile": [ "http://hl7.org/fhir/us/core/StructureDefinition/us-core-encounter" ],
        "tag": [ {
          "system": "https://ncqa.org/fhir/CodeSystem/synthea-state-id",
          "code": "4adb7488-b173-4413-88ce-4f0d1eec95ef",
          "display": "Synthea State Id that generated the resource"
        } ]
      },
      "identifier": [ {
        "use": "official",
        "system": "https://github.com/synthetichealth/synthea",
        "value": "122ae231-75de-503e-7718-04b9a38a3a8f"
      } ],
      "status": "finished",
      "class": {
        "system": "http://terminology.hl7.org/CodeSystem/v3-ActCode",
        "code": "AMB"
      },
      "type": [ {
        "coding": [ {
          "system": "http://www.ama-assn.org/go/cpt",
          "code": "99348"
        } ]
      } ],
      "subject": {
        "reference": "urn:uuid:86e31dbc-a80f-bf67-9244-fa5880a44236",
        "display": "Charmaine Jame Nolan"
      },
      "participant": [ {
        "type": [ {
          "coding": [ {
            "system": "http://terminology.hl7.org/CodeSystem/v3-ParticipationType",
            "code": "PPRF",
            "display": "primary performer"
          } ],
          "text": "primary performer"
        } ],
        "period": {
          "start": "2024-01-31T00:00:00+00:00",
          "end": "2024-01-31T00:15:00+00:00"
        },
        "individual": {
          "reference": "urn:uuid:5538f551-1633-35ca-a72a-a314c91a87ab",
          "display": "Dr. Daniela Hinojosa"
        }
      } ],
      "period": {
        "start": "2024-01-31T00:00:00+00:00",
        "end": "2024-01-31T00:15:00+00:00"
      },
      "location": [ {
        "location": {
          "reference": "Location?identifier=https://github.com/synthetichealth/synthea|d0e312f3-0a19-3089-af0e-db79b3aee7ab",
          "display": "\"HEALTHALLIANCE HOSPITALS, INC\""
        }
      } ],
      "serviceProvider": {
        "reference": "Organization?identifier=https://github.com/synthetichealth/synthea|363d3504-18f8-37de-8fbb-f52a59fd61b1",
        "display": "\"HEALTHALLIANCE HOSPITALS, INC\""
      }
    }
  }, {
    "fullUrl": "urn:uuid:e5eadf82-3470-366a-9508-fb9eb974505a",
    "resource": {
      "resourceType": "Condition",
      "id": "e5eadf82-3470-366a-9508-fb9eb974505a",
      "meta": {
        "profile": [ "http://hl7.org/fhir/us/core/StructureDefinition/us-core-condition" ],
        "tag": [ {
          "system": "https://ncqa.org/fhir/CodeSystem/synthea-state-id",
          "code": "9bf11b45-cf89-4e33-8947-85cf4023cf37",
          "display": "Synthea State Id that generated the resource"
        } ]
      },
      "clinicalStatus": {
        "coding": [ {
          "system": "http://terminology.hl7.org/CodeSystem/condition-clinical",
          "code": "active"
        } ]
      },
      "verificationStatus": {
        "coding": [ {
          "system": "http://terminology.hl7.org/CodeSystem/condition-ver-status",
          "code": "confirmed"
        } ]
      },
      "category": [ {
        "coding": [ {
          "system": "http://terminology.hl7.org/CodeSystem/condition-category",
          "code": "encounter-diagnosis",
          "display": "Encounter Diagnosis"
        } ]
      } ],
      "code": {
        "coding": [ {
          "system": "http://hl7.org/fhir/sid/icd-10-cm",
          "code": "O41.1292",
          "display": "[O41.1292] Chorioamnionitis, unspecified trimester, fetus 2"
        } ],
        "text": "[O41.1292] Chorioamnionitis, unspecified trimester, fetus 2"
      },
      "subject": {
        "reference": "urn:uuid:86e31dbc-a80f-bf67-9244-fa5880a44236"
      },
      "encounter": {
        "reference": "urn:uuid:122ae231-75de-503e-7718-04b9a38a3a8f"
      },
      "onsetDateTime": "2024-01-31T00:00:00+00:00",
      "recordedDate": "2024-01-31T00:00:00+00:00"
    }
  }, {
    "fullUrl": "urn:uuid:54fcd636-57c1-6e77-3684-b1f55543c74b",
    "resource": {
      "resourceType": "Claim",
      "id": "54fcd636-57c1-6e77-3684-b1f55543c74b",
      "meta": {
        "tag": [ {
          "system": "https://ncqa.org/fhir/CodeSystem/synthea-state-id",
          "code": "3676e0c0-e9c9-46f9-b422-db2b5a8d9425",
          "display": "Synthea State Id that generated the resource"
        }, {
          "system": "https://ncqa.org/fhir/CodeSystem/hedis-data-source",
          "code": "administrative"
        } ]
      },
      "status": "active",
      "type": {
        "coding": [ {
          "system": "http://terminology.hl7.org/CodeSystem/claim-type",
          "code": "institutional"
        } ]
      },
      "use": "claim",
      "patient": {
        "reference": "urn:uuid:86e31dbc-a80f-bf67-9244-fa5880a44236",
        "display": "Charmaine Nolan"
      },
      "billablePeriod": {
        "start": "2024-01-31T00:00:00+00:00",
        "end": "2024-01-31T00:15:00+00:00"
      },
      "created": "2024-01-31T00:15:00+00:00",
      "provider": {
        "reference": "Organization?identifier=https://github.com/synthetichealth/synthea|363d3504-18f8-37de-8fbb-f52a59fd61b1",
        "display": "\"HEALTHALLIANCE HOSPITALS, INC\""
      },
      "priority": {
        "coding": [ {
          "system": "http://terminology.hl7.org/CodeSystem/processpriority",
          "code": "normal"
        } ]
      },
      "diagnosis": [ {
        "sequence": 1,
        "diagnosisReference": {
          "reference": "urn:uuid:a83ce780-4bcb-9ab8-c467-ea4a5d7bd528",
          "display": "Opioid Abuse & Dep ICD 10 Dx Only"
        }
      } ],
      "item": [ {
        "sequence": 1,
        "diagnosisSequence": [ 1 ],
        "productOrService": {
          "coding": [ {
            "system": "http://www.ama-assn.org/go/cpt",
            "code": "99348"
          } ]
        },
        "servicedPeriod": {
          "start": "2024-01-31T00:00:00+00:00",
          "end": "2024-01-31T00:15:00+00:00"
        }
      } ]
    }
  }, {
    "fullUrl": "urn:uuid:a83ce780-4bcb-9ab8-c467-ea4a5d7bd528",
    "resource": {
      "resourceType": "Condition",
      "id": "a83ce780-4bcb-9ab8-c467-ea4a5d7bd528",
      "meta": {
        "profile": [ "http://hl7.org/fhir/us/core/StructureDefinition/us-core-condition" ],
        "tag": [ {
          "system": "https://ncqa.org/fhir/CodeSystem/synthea-state-id",
          "code": "6feebda2-5941-446c-a6ef-b6786b3f1544",
          "display": "Synthea State Id that generated the resource"
        } ]
      },
      "clinicalStatus": {
        "coding": [ {
          "system": "http://terminology.hl7.org/CodeSystem/condition-clinical",
          "code": "active"
        } ]
      },
      "verificationStatus": {
        "coding": [ {
          "system": "http://terminology.hl7.org/CodeSystem/condition-ver-status",
          "code": "confirmed"
        } ]
      },
      "category": [ {
        "coding": [ {
          "system": "http://terminology.hl7.org/CodeSystem/condition-category",
          "code": "encounter-diagnosis",
          "display": "Encounter Diagnosis"
        } ]
      } ],
      "code": {
        "coding": [ {
          "system": "http://hl7.org/fhir/sid/icd-10-cm",
          "code": "F11.221",
          "display": "[F11.221] Opioid dependence with intoxication delirium"
        } ],
        "text": "[F11.221] Opioid dependence with intoxication delirium"
      },
      "subject": {
        "reference": "urn:uuid:86e31dbc-a80f-bf67-9244-fa5880a44236"
      },
      "onsetDateTime": "2024-01-31T00:00:00+00:00",
      "recordedDate": "2024-01-31T00:00:00+00:00"
    }
  }, {
    "fullUrl": "urn:uuid:8414c0e2-d406-f98e-4665-6a431fab4129",
    "resource": {
      "resourceType": "Encounter",
      "id": "8414c0e2-d406-f98e-4665-6a431fab4129",
      "meta": {
        "profile": [ "http://hl7.org/fhir/us/core/StructureDefinition/us-core-encounter" ],
        "tag": [ {
          "system": "https://ncqa.org/fhir/CodeSystem/synthea-state-id",
          "code": "dc0a4bc7-7da2-4029-b73e-839f4f72238c",
          "display": "Synthea State Id that generated the resource"
        } ]
      },
      "identifier": [ {
        "use": "official",
        "system": "https://github.com/synthetichealth/synthea",
        "value": "8414c0e2-d406-f98e-4665-6a431fab4129"
      } ],
      "status": "finished",
      "class": {
        "system": "http://terminology.hl7.org/CodeSystem/v3-ActCode",
        "code": "AMB"
      },
      "type": [ {
        "coding": [ {
          "system": "https://www.nubc.org/CodeSystem/RevenueCodes",
          "code": "0153"
        } ]
      } ],
      "subject": {
        "reference": "urn:uuid:86e31dbc-a80f-bf67-9244-fa5880a44236",
        "display": "Charmaine Jame Nolan"
      },
      "participant": [ {
        "type": [ {
          "coding": [ {
            "system": "http://terminology.hl7.org/CodeSystem/v3-ParticipationType",
            "code": "PPRF",
            "display": "primary performer"
          } ],
          "text": "primary performer"
        } ],
        "period": {
          "start": "2024-03-31T00:00:00+00:00",
          "end": "2024-03-31T00:15:00+00:00"
        },
        "individual": {
          "reference": "urn:uuid:5538f551-1633-35ca-a72a-a314c91a87ab",
          "display": "Dr. Daniela Hinojosa"
        }
      } ],
      "period": {
        "start": "2024-03-31T00:00:00+00:00",
        "end": "2024-03-31T00:15:00+00:00"
      },
      "location": [ {
        "location": {
          "reference": "Location?identifier=https://github.com/synthetichealth/synthea|d0e312f3-0a19-3089-af0e-db79b3aee7ab",
          "display": "\"HEALTHALLIANCE HOSPITALS, INC\""
        }
      } ],
      "serviceProvider": {
        "reference": "Organization?identifier=https://github.com/synthetichealth/synthea|363d3504-18f8-37de-8fbb-f52a59fd61b1",
        "display": "\"HEALTHALLIANCE HOSPITALS, INC\""
      }
    }
  }, {
    "fullUrl": "urn:uuid:490c733a-d0c2-4faa-ad4f-21e623737e6e",
    "resource": {
      "resourceType": "Procedure",
      "id": "490c733a-d0c2-4faa-ad4f-21e623737e6e",
      "meta": {
        "profile": [ "http://hl7.org/fhir/us/core/StructureDefinition/us-core-procedure" ],
        "tag": [ {
          "system": "https://ncqa.org/fhir/CodeSystem/synthea-state-id",
          "code": "dbc86cb1-6aaf-4a23-80c9-6a0ee22d3f50",
          "display": "Synthea State Id that generated the resource"
        } ]
      },
      "status": "completed",
      "code": {
        "coding": [ {
          "system": "https://www.cms.gov/Medicare/Coding/HCPCSReleaseCodeSets",
          "code": "G0182",
          "display": "Physician supervision of a patient under a medicare-approved hospice (patient not present) requiring complex and multidisciplinary care modalities involving regular physician development and/or revision of care plans, review of subsequent reports of patient status, review of laboratory and other studies, communication (including telephone calls) with other health care professionals involved in the patient\\u0027s care, integration of new information into the medical treatment plan and/or adjustment of medical therapy, within a calendar month, 30 minutes or more (G0182)"
        } ],
        "text": "Physician supervision of a patient under a medicare-approved hospice (patient not present) requiring complex and multidisciplinary care modalities involving regular physician development and/or revision of care plans, review of subsequent reports of patient status, review of laboratory and other studies, communication (including telephone calls) with other health care professionals involved in the patient\\u0027s care, integration of new information into the medical treatment plan and/or adjustment of medical therapy, within a calendar month, 30 minutes or more (G0182)"
      },
      "subject": {
        "reference": "urn:uuid:86e31dbc-a80f-bf67-9244-fa5880a44236"
      },
      "encounter": {
        "reference": "urn:uuid:8414c0e2-d406-f98e-4665-6a431fab4129"
      },
      "performedPeriod": {
        "start": "2024-03-31T00:00:00+00:00",
        "end": "2024-03-31T00:15:00+00:00"
      },
      "location": {
        "reference": "Location?identifier=https://github.com/synthetichealth/synthea|d0e312f3-0a19-3089-af0e-db79b3aee7ab",
        "display": "\"HEALTHALLIANCE HOSPITALS, INC\""
      }
    }
  }, {
    "fullUrl": "urn:uuid:63403f09-03bc-2e73-e097-32923c2ec855",
    "resource": {
      "resourceType": "Coverage",
      "id": "63403f09-03bc-2e73-e097-32923c2ec855",
      "type": {
        "coding": [ {
          "system": "https://ncqa.org/fhir/codesystem/hedis-coverage-type",
          "code": "MOS"
        } ]
      },
      "beneficiary": {
        "reference": "urn:uuid:86e31dbc-a80f-bf67-9244-fa5880a44236",
        "display": "Charmaine Jame Nolan"
      },
      "period": {
        "start": "2024-01-01T00:00:00+00:00",
        "end": "2024-12-31T00:00:00+00:00"
      }
    }
  }, {
    "fullUrl": "urn:uuid:add33bb5-dd41-3fef-ecf4-aa4e25c38053",
    "resource": {
      "resourceType": "Coverage",
      "id": "add33bb5-dd41-3fef-ecf4-aa4e25c38053",
      "type": {
        "coding": [ {
          "system": "http://terminology.hl7.org/CodeSystem/v3-ActCode",
          "code": "MCPOL"
        } ]
      },
      "beneficiary": {
        "reference": "urn:uuid:86e31dbc-a80f-bf67-9244-fa5880a44236",
        "display": "Charmaine Jame Nolan"
      },
      "period": {
        "start": "2024-01-01T00:00:00+00:00",
        "end": "2024-12-31T00:00:00+00:00"
      }
    }
  }, {
    "fullUrl": "urn:uuid:null",
    "resource": {
      "resourceType": "MeasureReport",
      "status": "complete",
      "type": "individual",
      "measure": "\"http://fhir.ncqa.org/measures/hedis/aab_hedis_my2023\""
    }
  } ]
}
